[
  {
    "category": "Error Correction",
    "question": "相殺誤り（counterbalancing error）とは次のどれか：",
    "options": [
      {
        "text": "2会計期間内で自動的に相殺される誤り",
        "correct": true
      },
      {
        "text": "自己修正されず、無限に存続する誤り",
        "correct": false
      },
      {
        "text": "損益計算書にのみ影響する誤り",
        "correct": false
      },
      {
        "text": "貸借対照表にのみ影響する誤り",
        "correct": false
      }
    ],
    "explanation": "相殺誤りは2会計期間内で自動的に相殺される誤りである。例えば、第1年末の棚卸資産を過大計上すると第1年純利益を過大にし、第2年純利益を同額だけ過小にする（第1年の期末 = 第2年の期首のため）。"
  },
  {
    "category": "Error Correction",
    "question": "非相殺誤り（non-counterbalancing error）とは次のどれか：",
    "options": [
      {
        "text": "自動的には修正されず、前期修正が必要な誤り",
        "correct": true
      },
      {
        "text": "翌期に自動的に修正される誤り",
        "correct": false
      },
      {
        "text": "当期の財務諸表にのみ影響する誤り",
        "correct": false
      },
      {
        "text": "重要でなく、修正が不要な誤り",
        "correct": false
      }
    ],
    "explanation": "非相殺誤りは修正されるまで存続する。例：資産の減価償却を怠ると、すべての以後の期間に影響する。各期間の利益が減価償却費分だけ過大となり、誤りが発見・修正されるまで続く。"
  },
  {
    "category": "Error Correction",
    "question": "第1年末の期末棚卸資産が過小だった場合、第1年への影響は：",
    "options": [
      {
        "text": "売上原価が過大となり、純利益が過小となる",
        "correct": true
      },
      {
        "text": "売上原価が過小となり、純利益が過大となる",
        "correct": false
      },
      {
        "text": "売上原価と純利益がともに過小となる",
        "correct": false
      },
      {
        "text": "第1年の財務諸表に影響なし",
        "correct": false
      }
    ],
    "explanation": "売上原価 = 期首棚卸 + 仕入 - 期末棚卸。期末棚卸が過小の場合、売上原価は過大となり、売上総利益と純利益は過小となる。これは第2年に逆転する相殺誤りである。"
  },
  {
    "category": "Error Correction",
    "question": "第1年末の期末棚卸資産が過小だった場合、第2年への影響は：",
    "options": [
      {
        "text": "期首棚卸が過小となり、売上原価が過小、純利益が過大となる",
        "correct": true
      },
      {
        "text": "売上原価が過大となり、純利益が過小となる",
        "correct": false
      },
      {
        "text": "第2年に影響なし",
        "correct": false
      },
      {
        "text": "期首棚卸が過大となり、売上原価が過大となる",
        "correct": false
      }
    ],
    "explanation": "第1年の期末棚卸が第2年の期首棚卸になる。第2年の期首棚卸が過小の場合、売上原価 = 過小期首 + 仕入 - 期末 = 過小な売上原価、過大な純利益となる。これが相殺効果。"
  },
  {
    "category": "Error Correction",
    "question": "前払費用を支払時に費用として記録した場合（修正漏れ）、影響は：",
    "options": [
      {
        "text": "当期の費用が過大となり、資産が過小となる",
        "correct": true
      },
      {
        "text": "費用が過小となり、資産が過大となる",
        "correct": false
      },
      {
        "text": "誤りなし - 正しい処理である",
        "correct": false
      },
      {
        "text": "負債が過大となる",
        "correct": false
      }
    ],
    "explanation": "前払費用は消費されるまで資産であるべき。支払時に費用記録すると当期費用を過大、当期資産を過小にする。これは相殺誤り：翌期の費用が同額だけ過小となる。"
  },
  {
    "category": "Error Correction",
    "question": "期末の未収収益の計上漏れは次の結果をもたらす：",
    "options": [
      {
        "text": "当期の収益と資産がともに過小となる",
        "correct": true
      },
      {
        "text": "収益と負債がともに過小となる",
        "correct": false
      },
      {
        "text": "収益が過大となり、費用が過小となる",
        "correct": false
      },
      {
        "text": "現金未受領のため影響なし",
        "correct": false
      }
    ],
    "explanation": "未収収益（稼得済みだが未受領・未記録）は収益と売掛金の両方を増加させるべき。記録しないと両方が過小となる。翌期に現金を受領した時、収益が過大になる（相殺）。"
  },
  {
    "category": "Error Correction",
    "question": "前期修正（prior period adjustment）はどこに記載されるか：",
    "options": [
      {
        "text": "繰越利益剰余金計算書（または株主資本等変動計算書）の期首残高に対する修正として",
        "correct": true
      },
      {
        "text": "当期の損益計算書",
        "correct": false
      },
      {
        "text": "貸借対照表の独立項目",
        "correct": false
      },
      {
        "text": "キャッシュフロー計算書",
        "correct": false
      }
    ],
    "explanation": "前期修正は重要な誤りの修正で期首繰越利益剰余金残高を修正する。税引後純額で繰越利益剰余金計算書（または株主資本等変動計算書）に記載され、当期の損益計算書には記載しない。"
  },
  {
    "category": "Error Correction",
    "question": "減価償却費の計上漏れは次のどれの例か：",
    "options": [
      {
        "text": "非相殺誤り",
        "correct": true
      },
      {
        "text": "相殺誤り",
        "correct": false
      },
      {
        "text": "財務諸表に影響のない誤り",
        "correct": false
      },
      {
        "text": "貸借対照表にのみ影響する誤り",
        "correct": false
      }
    ],
    "explanation": "減価償却費の計上漏れは修正されるまで毎期に影響する（資産過大、資本過大、利益過大、減価償却費過小）。資産の帳簿価額が誤りを蓄積するため自己修正しない。"
  },
  {
    "category": "Error Correction",
    "question": "設備の購入を保守費用として記録した場合、この誤りは次をもたらす：",
    "options": [
      {
        "text": "誤りの発生年度において、費用が過大、資産が過小、純資産が過小となる",
        "correct": true
      },
      {
        "text": "費用が過小となり、資産が過大となる",
        "correct": false
      },
      {
        "text": "誤りなし - 保守と設備はともに費用である",
        "correct": false
      },
      {
        "text": "貸借対照表にのみ影響する",
        "correct": false
      }
    ],
    "explanation": "資本的支出（設備）は資産であるべき。直ちに費用処理すると費用が過大、資産と純利益（したがって繰越利益剰余金）が過小となる。これは非相殺誤りである。"
  },
  {
    "category": "Error Correction",
    "question": "第1年の帳簿が締切られた後、期末棚卸資産を50,000円過大計上していた誤りが第2年に発見された。第2年の帳簿がまだ開いている場合：",
    "options": [
      {
        "text": "第2年の期首繰越利益剰余金と棚卸資産記録を修正する。前期修正は不要。",
        "correct": true
      },
      {
        "text": "繰越利益剰余金計算書に前期修正として記載する",
        "correct": false
      },
      {
        "text": "第1年の財務諸表を修正再表示する",
        "correct": false
      },
      {
        "text": "相殺されるため誤りを無視する",
        "correct": false
      }
    ],
    "explanation": "当期（第2年）の帳簿がまだ開いている場合、誤りは第2年の期首残高を修正することで修正できる。これは相殺誤りなので、期首繰越利益と棚卸資産を直接修正でき、前期修正は不要。"
  },
  {
    "category": "Error Correction",
    "question": "企業が期末に80,000円の未払給与の見落としをした。影響は：",
    "options": [
      {
        "text": "費用が過小、負債が過小、純利益が過大となる",
        "correct": true
      },
      {
        "text": "費用が過大、負債が過大となる",
        "correct": false
      },
      {
        "text": "資産が過小、純資産が過大となる",
        "correct": false
      },
      {
        "text": "現金未支払のため純利益に影響なし",
        "correct": false
      }
    ],
    "explanation": "未記録の未払給与とは：(1) 給与費用が過小（不足費用）、(2) 未払給与が過小（不足負債）、(3) 純利益が過大、(4) 繰越利益剰余金が過大。これは相殺誤り。"
  },
  {
    "category": "Error Correction",
    "question": "過去3年間、減価償却費が毎年20,000円過小だった場合、第4年に発見された時の修正は：",
    "options": [
      {
        "text": "第4年期首繰越利益剰余金に対する60,000円（税引後）の前期修正",
        "correct": true
      },
      {
        "text": "当期に20,000円の追加減価償却費を計上して修正する",
        "correct": false
      },
      {
        "text": "過去3年間の財務諸表をすべて修正再表示する",
        "correct": false
      },
      {
        "text": "当期に60,000円の減価償却費を計上する",
        "correct": false
      }
    ],
    "explanation": "これは非相殺誤り。3年間 x 20,000 = 60,000 の累積影響を前期修正（税引後）として修正する必要がある。資産の帳簿価額も減価償却累計額を減額して修正する。"
  },
  {
    "category": "Error Correction",
    "question": "次のうち、試算表の作成では発見できない誤りはどれか：",
    "options": [
      {
        "text": "金額は正しいが間違った勘定に記録された取引（借方・貸方ともに正しい場合）",
        "correct": true
      },
      {
        "text": "借方と貸方が不一致の仕訳",
        "correct": false
      },
      {
        "text": "取引の借方側のみが転記された",
        "correct": false
      },
      {
        "text": "仕訳で金額が誤って計算された",
        "correct": false
      }
    ],
    "explanation": "試算表は借方合計 = 貸方合計を確認する。原則的誤り（勘定が違うが金額は正しい）は借貸の均衡を維持するため、試算表では検出されない。"
  },
  {
    "category": "Error Correction",
    "question": "定期棚卸法で期首棚卸資産を過大計上すると次の結果となる：",
    "options": [
      {
        "text": "売上原価が過大となり、純利益が過小となる",
        "correct": true
      },
      {
        "text": "売上原価が過小となり、純利益が過大となる",
        "correct": false
      },
      {
        "text": "売上原価と純利益に影響なし",
        "correct": false
      },
      {
        "text": "売上原価が過小となり、期末棚卸が過大となる",
        "correct": false
      }
    ],
    "explanation": "売上原価 = 期首棚卸 + 仕入 - 期末棚卸。期首棚卸の過大は直接売上原価を増加させ、売上総利益と純利益を減少させる。これは相殺誤り。"
  },
  {
    "category": "Error Correction",
    "question": "機械の購入を土地の借方に記録した場合、影響は：",
    "options": [
      {
        "text": "総資産は正しいが内訳が誤り。減価償却費が過小となる。",
        "correct": true
      },
      {
        "text": "総資産が過大となる",
        "correct": false
      },
      {
        "text": "総資産が過小となる",
        "correct": false
      },
      {
        "text": "誤りなし - 土地と機械は同じ勘定である",
        "correct": false
      }
    ],
    "explanation": "これは分類の誤りであり、金額の誤りではない。総資産は当初正しい。ただし、土地は減価償却されず、機械は減価償却されるべき。将来の減価償却費が過小となり、純利益と資産が以後の期間で過大になる。"
  }
]
